<?xml version="1.0" encoding="windows-1251"?>
<TimeChronology xmlns:xsi="http://www.w3.org/2001/XMLSchema-instance" xmlns:xsd="http://www.w3.org/2001/XMLSchema">
  <TSequences>
    <TSequence>
      <TEvents>
        <TEvent>
          <Moment>0</Moment>
          <Location>
            <x>-9.12</x>
            <y>1.54</y>
          </Location>
          <Action>Appear0</Action>
        </TEvent>
        <TEvent>
          <Moment>0.298600554</Moment>
          <Location>
            <x>-8.047046</x>
            <y>1.56822288</y>
          </Location>
          <Action>ChangeLocation</Action>
        </TEvent>
        <TEvent>
          <Moment>0.4777002</Moment>
          <Location>
            <x>-6.87075424</x>
            <y>1.56824374</y>
          </Location>
          <Action>ChangeLocation</Action>
        </TEvent>
        <TEvent>
          <Moment>0.656800151</Moment>
          <Location>
            <x>-5.577026</x>
            <y>1.5682466</y>
          </Location>
          <Action>ChangeLocation</Action>
        </TEvent>
        <TEvent>
          <Moment>0.8359001</Moment>
          <Location>
            <x>-4.2378006</x>
            <y>1.56824672</y>
          </Location>
          <Action>ChangeLocation</Action>
        </TEvent>
        <TEvent>
          <Moment>1.01500046</Moment>
          <Location>
            <x>-2.88094783</x>
            <y>1.56824672</y>
          </Location>
          <Action>ChangeLocation</Action>
        </TEvent>
        <TEvent>
          <Moment>1.19409978</Moment>
          <Location>
            <x>-1.51726651</x>
            <y>1.56824672</y>
          </Location>
          <Action>ChangeLocation</Action>
        </TEvent>
        <TEvent>
          <Moment>1.37320018</Moment>
          <Location>
            <x>-0.15093945</x>
            <y>1.56824672</y>
          </Location>
          <Action>ChangeLocation</Action>
        </TEvent>
        <TEvent>
          <Moment>1.55229974</Moment>
          <Location>
            <x>1.12754977</x>
            <y>1.38824677</y>
          </Location>
          <Action>ChangeLocation</Action>
        </TEvent>
        <TEvent>
          <Moment>1.67169952</Moment>
          <Location>
            <x>2.23966742</x>
            <y>0.7762468</y>
          </Location>
          <Action>ChangeLocation</Action>
        </TEvent>
        <TEvent>
          <Moment>1.79109943</Moment>
          <Location>
            <x>3.4396677</x>
            <y>-0.267753154</y>
          </Location>
          <Action>ChangeLocation</Action>
        </TEvent>
        <TEvent>
          <Moment>1.91049886</Moment>
          <Location>
            <x>4.639667</x>
            <y>-1.74375343</y>
          </Location>
          <Action>ChangeLocation</Action>
        </TEvent>
        <TEvent>
          <Moment>1.97019887</Moment>
          <Location>
            <x>5.23966646</x>
            <y>-2.64375353</y>
          </Location>
          <Action>ChangeLocation</Action>
        </TEvent>
        <TEvent>
          <Moment>2.02989864</Moment>
          <Location>
            <x>5.839666</x>
            <y>-3.65175366</y>
          </Location>
          <Action>ChangeLocation</Action>
        </TEvent>
        <TEvent>
          <Moment>2.08959913</Moment>
          <Location>
            <x>6.43966532</x>
            <y>-4.767754</y>
          </Location>
          <Action>ChangeLocation</Action>
        </TEvent>
        <TEvent>
          <Moment>2.3283987</Moment>
          <Location>
            <x>7.57234669</x>
            <y>-5.28175259</y>
          </Location>
          <Action>ChangeLocation</Action>
        </TEvent>
        <TEvent>
          <Moment>2.507499</Moment>
          <Location>
            <x>8.718893</x>
            <y>-5.28169441</y>
          </Location>
          <Action>ChangeLocation</Action>
        </TEvent>
        <TEvent>
          <Moment>2.68659878</Moment>
          <Location>
            <x>10.0010986</x>
            <y>-5.28168631</y>
          </Location>
          <Action>ChangeLocation</Action>
        </TEvent>
        <TEvent>
          <Moment>4.457699</Moment>
          <Location>
            <x>10.7388792</x>
            <y>-5.28168631</y>
          </Location>
          <Action>Return</Action>
        </TEvent>
      </TEvents>
    </TSequence>
  </TSequences>
</TimeChronology>